data_oracle/__init__.py
data_oracle/.idea/.gitignore
data_oracle/.idea/dataOracle.iml
data_oracle/.idea/misc.xml
data_oracle/.idea/modules.xml
data_oracle/.idea/workspace.xml
data_oracle/.idea/inspectionProfiles/Project_Default.xml
data_oracle/.idea/inspectionProfiles/profiles_settings.xml
data_oracle/connectors/__init__.py
data_oracle/connectors/baseconnector.py
data_oracle/connectors/connection_class.py
data_oracle/connectors/sqlalchemyconnector.py
data_oracle/db_schema/__init__.py
data_oracle/db_schema/base_db_class.py
data_oracle/db_schema/database_schema.py
data_oracle/db_schema/filterobject.py
data_oracle/db_schema/foreign_key_schema.py
data_oracle/enums/__init__.py
data_oracle/enums/base_enum.py
data_oracle/enums/filter_enum.py
data_oracle/enums/llm_enums.py
data_oracle/enums/sql_enums.py
data_oracle/query_generation/__init__.py
data_oracle/query_generation/pipeline/__init__.py
data_oracle/query_generation/pipeline/basepipeline.py
data_oracle/query_generation/pipeline/local_pipeline.py
data_oracle/query_generation/pipeline/prompts.py
data_oracle-0.0.3.dist-info/METADATA
data_oracle-0.0.3.dist-info/WHEEL
data_oracle-0.0.3.dist-info/licenses/LICENSE
data_oracle-0.0.3.dist-info/RECORD
